{
  "results": [
    {
      "book": "VibhaktiForms",
      "id": "67285",
      "key": "idam-makaranta-pumlinga",
      "order": 1,
      "tags": [
        "सर्वनाम"
      ],
      "text": "मकारान्तः पुंलिङ्गः इदम्-शब्दः"
    }
  ],
  "related": [
    {
      "book": "VibhaktiFormEntry",
      "id": "67286",
      "key": "idam-makaranta-pumlinga",
      "order": 1,
      "tags": [
        "सर्वनाम",
        "Vibhakti Form Entry"
      ],
      "text": "अयम्|इमौ|इमे|-|-|-|इमम्-एनम्|इमौ-एनौ|इमान्-एनान्|अनेन-एनेन|आभ्याम्|एभिः|अस्मै|आभ्याम्|एभ्यः|अस्मात्-अस्माद्|आभ्याम्|एभ्यः|अस्य|अनयोः-एनयोः|एषाम्|अस्मिन्|अनयोः-एनयोः|एषु"
    }
  ]
}