{
  "results": [
    {
      "book": "YogaSutras",
      "id": "64078",
      "key": "2-21",
      "order": 72,
      "tags": [
        "Pada 2",
        "Sutra 21"
      ],
      "text": "तदर्थ एव दृश्यस्याऽऽत्मा ॥ २-२१ ॥"
    }
  ],
  "related": [
    {
      "book": "YS_Com_YogaChandrika",
      "id": "66769",
      "key": "2-21",
      "order": 221,
      "tags": [
        "2-21",
        "Pada 2",
        "Sutra 21",
        "Yoga Sutra Commentary"
      ],
      "text": "\nतदर्थ एव दृश्यस्याऽऽत्मा ॥ २१ ॥\n"
    },
    {
      "book": "YS_Com_YogaSudhakara",
      "id": "66531",
      "key": "2-21",
      "order": 221,
      "tags": [
        "2-21",
        "Pada 2",
        "Sutra 21",
        "Yoga Sutra Commentary"
      ],
      "text": "\nइत्थं दृश्यद्रष्टारवभिधाय तयोः शेषशेषित्वमभिधातुमाह –\nतदर्थ एव दृश्यस्याऽऽत्मा ॥ २१ ॥\nदृश्यस्य भोग्यस्यात्मा स्वरूपं द्रष्ट्रर्थमेव न स्वार्थम्, अचेतनत्वादित्यर्थः ॥ २१ ॥\nउक्तमन्यत्रातिदिशति –\nएतेन स्वीयशब्दस्पर्शरूपरसगन्धानां संयमाच्छ्रोत्राद्यग्राह्यत्वसिद्धिरुक्ता भवतीति वेदितव्यम् ॥\n"
    },
    {
      "book": "YS_Com_Vritti",
      "id": "66384",
      "key": "2-21",
      "order": 221,
      "tags": [
        "2-21",
        "Pada 2",
        "Sutra 21",
        "Yoga Sutra Commentary"
      ],
      "text": "\nअथ संयोगाङ्गदृश्यस्य द्रष्ट्रर्थत्वमाह –\nतदर्थ एव दृश्यस्याऽऽत्मा ॥ २१ ॥\nतस्य द्रष्टुरर्थः प्रयोजनं भोगापवर्गावेव प्रयोजनं यस्य स तदर्थः । द्रष्टुर्भोगापवर्गफलकं दृश्यस्यात्मा स्वरूपं कार्यकारणात्मकं गुणत्रयं न स्वार्थमित्यर्थः । यतो दृश्यमेव पुरुषस्य भोग्यम् । यतो रूपशब्दादयो विषयाः सुखदुःखात्मतयानुकूलयितारः प्रतिकूलयितारश्च । अनुकूलनीयादिश्चेतनः पुरुष एव । न स्वात्मा कर्तृकर्मविरोधात् । किं च यतो दृश्यस्वरूपं यावत्पुरुषार्थमनुवर्तते तन्निवृत्तौ च निवर्ततेऽतो न स्वार्थम्। तदनेन गुणाः परार्थाः संहत्यकारित्वाच्छय्यादिवदित्यनुमानं प्रकृत्याद्यतिरिक्तपुरुषे मानमपि दंशितम् । संहत्यकारित्वं स्वकार्ये सहकारिसापेक्षम् ॥ २१ ॥\n"
    },
    {
      "book": "YS_Com_SutrarthaBodhini",
      "id": "66126",
      "key": "2-21",
      "order": 221,
      "tags": [
        "2-21",
        "Pada 2",
        "Sutra 21",
        "Yoga Sutra Commentary"
      ],
      "text": "\nतयोः शेषशेषित्वमाह –\nतदर्थ एव दृश्यस्याऽऽत्मा ॥ २१ ॥\nदृश्यस्य भोग्यस्य स्वरूपं द्रष्ट्रर्थमेव, न स्वार्थम् अचेतनत्वादित्यर्थः ॥ २१ ॥\n"
    },
    {
      "book": "YS_Com_SiddhantaChandrika",
      "id": "65993",
      "key": "2-21",
      "order": 221,
      "tags": [
        "2-21",
        "Pada 2",
        "Sutra 21",
        "Yoga Sutra Commentary"
      ],
      "text": "\nप्रमाणं दर्शयति-\nतदर्थ एव दृश्यस्यात्मा॥२१॥\nतस्य पुरुषार्थः प्रयोजनं भोगापवर्गावेवार्थः प्रयोजनं यस्य स तथेति मध्यमलोपिसमासः। पुरुषस्य भोगापवर्गप्रयोजनक एव दृश्यस्यात्मा स्वरूपं कार्यकारणात्मकं गुणत्रयं, न स्वार्थमित्यर्थः। तथा च, गुणाः परार्थाः, संहत्यकारित्वात्। शय्यादिवदित्याद्यनुमानेन दृश्यातिरिक्तस्य पुरुषस्य सिद्धिरिति भावः। तदर्थमेव दृश्यमित्येतावन्मात्रेणैव निर्वाहेऽप्यात्मपदं धात्वर्थे दर्शने तदर्थत्वान्वयभ्रमनिरासाय प्रयुक्तमिति दिक्॥२१॥\n"
    },
    {
      "book": "YS_Com_Pradipika",
      "id": "65883",
      "key": "2-21",
      "order": 221,
      "tags": [
        "2-21",
        "Pada 2",
        "Sutra 21",
        "Yoga Sutra Commentary"
      ],
      "text": "\nकायरूपसंयमात्तद्ग्राह्यशक्तिस्तम्भे चक्षुष्प्रकाशासंप्रयोगेऽन्तर्धानम् ॥ २१ ॥\nस्वशरीरस्य रूपे संयमात्कारणाद्यशेषविशेषैः साक्षात्कृते सति संकल्पमात्रेण स्वकीयरूपस्य दृश्यताशक्तिं परचक्षुःसयोगयोग्यतां स्तभ्नाति प्रतिबन्धाति । ततश्चक्षुःकिरणैरसंयोगेऽन्तर्धानं योगिन उत्पद्यते । दिवान्धेनेव केनाप्यसौ न दृश्यत इत्यर्थः । एतेन शब्दाद्यन्तर्धानमुक्तम् ॥ २० ॥\n"
    },
    {
      "book": "YS_Com_ManiPrabha",
      "id": "65584",
      "key": "2-21",
      "order": 221,
      "tags": [
        "2-21",
        "Pada 2",
        "Sutra 21",
        "Yoga Sutra Commentary"
      ],
      "text": "\nएवं दृश्यद्रष्टारावुक्तौ । तयोः शेषशेषित्वमाह- \nतदर्थ एव दृश्यस्यात्मा ॥ (२१ )\nदृश्यस्य- भोग्यस्य स्वरूपं द्रष्टुरर्थमेव, न स्वार्थम् अचेतनत्वादित्यर्थः ॥\n"
    },
    {
      "book": "YS_Com_VyasaBhashya",
      "id": "65371",
      "key": "2-21",
      "order": 221,
      "tags": [
        "2-21",
        "Pada 2",
        "Sutra 21",
        "Yoga Sutra Commentary"
      ],
      "text": "\nतदर्थ एव दृश्यस्याऽऽत्मा ॥ २१ ॥ \nदृशिरूपस्य पुरुषस्य कर्मरूपतामापन्नं दृश्यमिति तदर्थ एव दृश्यस्याऽऽत्मा भवति। स्वरूपं भवतीत्यर्थः। स्वरूपं तु पररूपेण प्रतिलब्धात्मकं भोगापवर्गार्थतायां कृतायां पुरुषेण न दृश्यत इति। स्वरूपहानादस्य नाशः प्राप्तो न तु विनश्यति ॥ २१ ॥ \n"
    },
    {
      "book": "YS_Com_RajaMartandaBhashya",
      "id": "64972",
      "key": "2-21",
      "order": 221,
      "tags": [
        "2-21",
        "Pada 2",
        "Sutra 21",
        "Yoga Sutra Commentary"
      ],
      "text": "\nस एव भोक्तेत्याह –\nतदर्थ एव दृश्यस्याऽऽत्मा ॥ २१ ॥ \nदृश्यस्य प्रागुक्तलक्षणस्याऽऽत्मा यत्स्वरूपं स तदर्थस्तस्य पुरुषस्य भोक्तृत्वसंपादनं नाम स्वार्थपरिहारेण प्रयोजम्। न हि प्रधानं प्रवर्तमानमात्मनः किंचित्प्रयोजनमपेक्ष्य प्रवर्तते किंतु पुरुषस्य भोक्तृत्वं संपादयितुमिति।\n"
    }
  ]
}