{
  "results": [
    {
      "book": "YogaSutras",
      "id": "64046",
      "key": "2-29",
      "order": 80,
      "tags": [
        "Pada 2",
        "Sutra 29"
      ],
      "text": "यमनियमासन​प्राणायामप्रत्याहार​धारणाध्यान​समाधयोऽष्टावङ्गानि ॥ २-२९ ॥"
    }
  ],
  "related": [
    {
      "book": "YS_Com_YogaChandrika",
      "id": "66737",
      "key": "2-29",
      "order": 229,
      "tags": [
        "2-29",
        "Pada 2",
        "Sutra 29",
        "Yoga Sutra Commentary"
      ],
      "text": "\nयमनियमासन​प्राणायामप्रत्याहार​धारणाध्यान​समाधयोऽष्टावङ्गानि ॥ २९ ॥\nकानि तानि योगाङ्गानीत्यपेक्षायां तान्याह- यमनियमेति सूत्रेण । तेषां व्याख्या अग्रिमसूत्राणि ॥ २९ ॥\n"
    },
    {
      "book": "YS_Com_YogaSudhakara",
      "id": "66514",
      "key": "2-29",
      "order": 229,
      "tags": [
        "2-29",
        "Pada 2",
        "Sutra 29",
        "Yoga Sutra Commentary"
      ],
      "text": "\nकानि पुनस्तानि योगाङ्गानीत्यपेक्षायामाह –\nयमनियमासन​प्राणायामप्रत्याहार​धारणाध्यान​समाधयोऽष्टावङ्गानि ॥ २९ ॥\n"
    },
    {
      "book": "YS_Com_Vritti",
      "id": "66307",
      "key": "2-29",
      "order": 229,
      "tags": [
        "2-29",
        "Pada 2",
        "Sutra 29",
        "Yoga Sutra Commentary"
      ],
      "text": "\nतत्र योगाङ्गान्याह –\nयमनियमासन​प्राणायामप्रत्याहार​धारणाध्यान​समाधयोऽष्टावङ्गानि ॥ २९ ॥\nएतानि ज्ञानस्येव योगस्यापि साधनतया योगाङ्गानि ॥ २९ ॥\n"
    },
    {
      "book": "YS_Com_SutrarthaBodhini",
      "id": "66213",
      "key": "2-29",
      "order": 229,
      "tags": [
        "2-29",
        "Pada 2",
        "Sutra 29",
        "Yoga Sutra Commentary"
      ],
      "text": "\nकानि योगाङ्गानीत्यत आह –\nयमनियमासन​प्राणायामप्रत्याहार​धारणाध्यान​समाधयोऽष्टावङ्गानि ॥ २९ ॥\nस्पष्टम् ॥ २९ ॥\n"
    },
    {
      "book": "YS_Com_SiddhantaChandrika",
      "id": "66038",
      "key": "2-29",
      "order": 229,
      "tags": [
        "2-29",
        "Pada 2",
        "Sutra 29",
        "Yoga Sutra Commentary"
      ],
      "text": "\nकानि पुनस्तानि साक्षाद्राजयोगस्याङ्गानि यैरशुद्धक्षये ज्ञानस्य दीप्तिस्तत्राह-\nयमनियमासनप्राणायामप्रत्याहारधारणाध्यानसमाधयोऽष्टावङ्गानि॥२९॥\nतत्र स्वत एव सफलत्वादत्यवश्यकाः सर्वमुमुक्षुजनसेव्याः आदौ, पश्चात् तत्सापेक्षा नियमाः। एतदुभयाधीनचित्तस्थैर्यसापेक्षाण्यासनानि। तत्सापेक्षः प्राणायामः। तत्सापेक्षः प्रत्याहारः। तत्सापेक्षा धारणा। तत्सापेक्षं ध्यानम्। तत्सापेक्षः समाधिः सविकल्प इत्यष्टौ साक्षात् परम्परया वा निर्विकल्पस्य समाधेरङ्गानीत्यर्थः। अष्टाङ्गमैथुने क्रियानिष्पत्तेरङ्गिनोऽङ्गत्ववत् समाधेरङ्गिनोऽङ्गत्वं वा बोध्यम्। तेन न कोऽपि दोषः॥२९॥\n"
    },
    {
      "book": "YS_Com_Pradipika",
      "id": "65786",
      "key": "2-29",
      "order": 229,
      "tags": [
        "2-29",
        "Pada 2",
        "Sutra 29",
        "Yoga Sutra Commentary"
      ],
      "text": "\nनाभिचक्रे कायव्यूहज्ञानम् ॥ २९ ॥\nकदलीकन्दवदादावुत्पन्नं नाभिकन्दरूपं चक्रं शरीरमध्यवर्ति यतः शाखापल्लवादिवच्छिरःपादादिकमवयवजातमूर्ध्वाधःपार्श्वेष्वाविर्भवति । तस्मिन्नाभिचक्रे संयमात्साक्षात्कृते कायस्थं पदार्थव्यूहं वातपित्तत्वगसृगादिरूपं साक्षात्क्रियते ॥ २८ ॥\n"
    },
    {
      "book": "YS_Com_ManiPrabha",
      "id": "65649",
      "key": "2-29",
      "order": 229,
      "tags": [
        "2-29",
        "Pada 2",
        "Sutra 29",
        "Yoga Sutra Commentary"
      ],
      "text": "\nकानि योगाङ्गानीत्यत आह- \nयमनियमासनप्राणायामप्रत्याहारधारणध्यानसमाधयोस्ष्टावङ्गानि ॥ ( २९ )\n"
    },
    {
      "book": "YS_Com_VyasaBhashya",
      "id": "65454",
      "key": "2-29",
      "order": 229,
      "tags": [
        "2-29",
        "Pada 2",
        "Sutra 29",
        "Yoga Sutra Commentary"
      ],
      "text": "\nतत्र योगाङ्गान्यवधार्यन्ते –\nयमनियमासन​प्राणायामप्रत्याहार​धारणाध्यान​समाधयोऽष्टावङ्गानि ॥ २९ ॥ \nयथाक्रममेषामनुष्ठानं स्वरूपं च वक्ष्यामः ॥ २९ ॥ \n"
    },
    {
      "book": "YS_Com_RajaMartandaBhashya",
      "id": "65066",
      "key": "2-29",
      "order": 229,
      "tags": [
        "2-29",
        "Pada 2",
        "Sutra 29",
        "Yoga Sutra Commentary"
      ],
      "text": "\nयोगाङ्गानुष्ठानादशुद्धिक्षय इत्युक्तं कानि पुनस्तानि योगाङ्गानीति तेषामुपद्देशमाह –\nयमनियमासन​प्राणायामप्रत्याहार​धारणाध्यान​समाधयोऽष्टावङ्गानि ॥ २९ ॥ \nइह कानिचित्समाधेः साक्षादुपकारकत्वेनान्तरङ्गाणि यथा धारणादीनि। कानिचित्प्रतिपक्षभूतहिंसादिवितर्कोन्मूलनद्वारेण समाधिमुपकुर्वन्ति। यथा यमनियमादीनि। तत्राऽऽसनादिनामुत्तरोत्तरमुपकारकत्वम्। तद्यथा सत्यासनजये प्राणायामस्थैर्यम्। एवमुत्तरत्रापि योज्यम्।\n"
    }
  ]
}